creepypasta/__init__.py
creepypasta/pasta_listings.py
creepypasta/pasta_stories.py
creepypasta-0.0.5.dist-info/LICENSE
creepypasta-0.0.5.dist-info/METADATA
creepypasta-0.0.5.dist-info/WHEEL
creepypasta-0.0.5.dist-info/top_level.txt
creepypasta-0.0.5.dist-info/RECORD
